{
  "variants": {
    "": [
      {
        "model": "jsg_core:block/ore/titanium/netherrack"
      },
      {
        "model": "jsg_core:block/ore/titanium/netherrack",
        "x": 90
      },
      {
        "model": "jsg_core:block/ore/titanium/netherrack",
        "x": 180
      },
      {
        "model": "jsg_core:block/ore/titanium/netherrack",
        "x": 270
      },
      {
        "model": "jsg_core:block/ore/titanium/netherrack",
        "y": 90
      },
      {
        "model": "jsg_core:block/ore/titanium/netherrack",
        "x": 90,
        "y": 90
      },
      {
        "model": "jsg_core:block/ore/titanium/netherrack",
        "x": 180,
        "y": 90
      },
      {
        "model": "jsg_core:block/ore/titanium/netherrack",
        "x": 270,
        "y": 90
      },
      {
        "model": "jsg_core:block/ore/titanium/netherrack",
        "y": 180
      },
      {
        "model": "jsg_core:block/ore/titanium/netherrack",
        "x": 90,
        "y": 180
      },
      {
        "model": "jsg_core:block/ore/titanium/netherrack",
        "x": 180,
        "y": 180
      },
      {
        "model": "jsg_core:block/ore/titanium/netherrack",
        "x": 270,
        "y": 180
      },
      {
        "model": "jsg_core:block/ore/titanium/netherrack",
        "y": 270
      },
      {
        "model": "jsg_core:block/ore/titanium/netherrack",
        "x": 90,
        "y": 270
      },
      {
        "model": "jsg_core:block/ore/titanium/netherrack",
        "x": 180,
        "y": 270
      },
      {
        "model": "jsg_core:block/ore/titanium/netherrack",
        "x": 270,
        "y": 270
      }
    ]
  }
}